MANIFEST.in
README.txt
setup.py
docs/HISTORY.txt
docs/LICENSE.txt
docs/TODO.txt
src/silva/__init__.py
src/silva.security.overview.egg-info/PKG-INFO
src/silva.security.overview.egg-info/SOURCES.txt
src/silva.security.overview.egg-info/dependency_links.txt
src/silva.security.overview.egg-info/namespace_packages.txt
src/silva.security.overview.egg-info/not-zip-safe
src/silva.security.overview.egg-info/requires.txt
src/silva.security.overview.egg-info/top_level.txt
src/silva/security/__init__.py
src/silva/security/overview/__init__.py
src/silva/security/overview/catalog.py
src/silva/security/overview/configure.zcml
src/silva/security/overview/ftesting.zcml
src/silva/security/overview/index.py
src/silva/security/overview/interfaces.py
src/silva/security/overview/service.png
src/silva/security/overview/service.py
src/silva/security/overview/subscribers.py
src/silva/security/overview/testing.py
src/silva/security/overview/service_templates/securityoverview.pt
src/silva/security/overview/tests/__init__.py
src/silva/security/overview/tests/test_func_service.py
src/silva/security/overview/tests/test_service.py