Metadata-Version: 1.1
Name: silva.security.overview
Version: 1.1.1
Summary: Extension providing a global overview of the permissions granted to users in the Silva CMS
Home-page: https://github.com/silvacms/silva.security.overview
Author: Infrae
Author-email: info@infrae.com
License: BSD
Keywords: silva cms zope security
Platform: UNKNOWN
Classifier: Framework :: Zope2
Classifier: License :: OSI Approved :: BSD License
Classifier: Programming Language :: Python
Classifier: Topic :: Software Development :: Libraries :: Python Modules
